Metadata-Version: 1.1
Name: SatelliteImage
Version: 0.1.27
Summary: Simple API provides a class to process satellite images
Home-page: https://github.com/dgketchum/satellite_image
Author: David Ketchum
Author-email: dgketchum@gmail.com
License: Apache
Download-URL: https://github.com/dgketchum/satellite_image/archive/0.1.27.tar.gz
Keywords: landsat download hydrology remote sensing
Platform: Posix; MacOS X; Windows
Classifier: Development Status :: 3 - Alpha
Classifier: Intended Audience :: Science/Research
Classifier: Topic :: Scientific/Engineering :: GIS
Classifier: License :: OSI Approved :: Apache Software License
Classifier: Programming Language :: Python :: 2.7
Classifier: Programming Language :: Python :: 3.6
